telegram/__init__.py
telegram/__main__.py
telegram/base.py
telegram/bot.py
telegram/botcommand.py
telegram/botcommandscope.py
telegram/callbackquery.py
telegram/chat.py
telegram/chataction.py
telegram/chatadministratorrights.py
telegram/chatinvitelink.py
telegram/chatjoinrequest.py
telegram/chatlocation.py
telegram/chatmember.py
telegram/chatmemberupdated.py
telegram/chatpermissions.py
telegram/choseninlineresult.py
telegram/constants.py
telegram/dice.py
telegram/error.py
telegram/forcereply.py
telegram/forumtopic.py
telegram/keyboardbutton.py
telegram/keyboardbuttonpolltype.py
telegram/loginurl.py
telegram/menubutton.py
telegram/message.py
telegram/messageautodeletetimerchanged.py
telegram/messageentity.py
telegram/messageid.py
telegram/parsemode.py
telegram/poll.py
telegram/proximityalerttriggered.py
telegram/py.typed
telegram/replykeyboardmarkup.py
telegram/replykeyboardremove.py
telegram/replymarkup.py
telegram/sentwebappmessage.py
telegram/update.py
telegram/user.py
telegram/userprofilephotos.py
telegram/version.py
telegram/videochat.py
telegram/voicechat.py
telegram/webappdata.py
telegram/webappinfo.py
telegram/webhookinfo.py
telegram/ext/__init__.py
telegram/ext/basepersistence.py
telegram/ext/callbackcontext.py
telegram/ext/callbackdatacache.py
telegram/ext/callbackqueryhandler.py
telegram/ext/chatjoinrequesthandler.py
telegram/ext/chatmemberhandler.py
telegram/ext/choseninlineresulthandler.py
telegram/ext/commandhandler.py
telegram/ext/contexttypes.py
telegram/ext/conversationhandler.py
telegram/ext/defaults.py
telegram/ext/dictpersistence.py
telegram/ext/dispatcher.py
telegram/ext/extbot.py
telegram/ext/filters.py
telegram/ext/handler.py
telegram/ext/inlinequeryhandler.py
telegram/ext/jobqueue.py
telegram/ext/messagehandler.py
telegram/ext/messagequeue.py
telegram/ext/picklepersistence.py
telegram/ext/pollanswerhandler.py
telegram/ext/pollhandler.py
telegram/ext/precheckoutqueryhandler.py
telegram/ext/regexhandler.py
telegram/ext/shippingqueryhandler.py
komi_san-0.1.dist-info/LICENSE.dual
komi_san-0.1.dist-info/METADATA
komi_san-0.1.dist-info/WHEEL
komi_san-0.1.dist-info/top_level.txt
komi_san-0.1.dist-info/RECORD
